jiraburnupanddown/__init__.py
jiraburnupanddown/fakejira.py
jiraburnupanddown/jiraburnupanddown.py
jiraburnupanddown/icons/document-save-as.png
jiraburnupanddown/icons/edit-copy.png
jiraburnupanddown-0.2.dist-info/DESCRIPTION.rst
jiraburnupanddown-0.2.dist-info/METADATA
jiraburnupanddown-0.2.dist-info/RECORD
jiraburnupanddown-0.2.dist-info/WHEEL
jiraburnupanddown-0.2.dist-info/entry_points.txt
jiraburnupanddown-0.2.dist-info/metadata.json
jiraburnupanddown-0.2.dist-info/top_level.txt
