Metadata-Version: 2.0
Name: jiraburnupanddown
Version: 0.2
Summary: A Scrum burndown chart for Jira that also keeps track of hours spent on a separate fixed-size budget
Home-page: https://github.com/Griffon26/jiraburnupanddown
Author: Maurice van der Pot
Author-email: griffon26@kfk4ever.com
License: GPLv3+
Platform: UNKNOWN
Classifier: Development Status :: 3 - Alpha
Classifier: Intended Audience :: Developers
Classifier: Topic :: Software Development
Classifier: License :: OSI Approved :: GNU General Public License v3 or later (GPLv3+)
Classifier: Programming Language :: Python :: 3 :: Only
Requires-Dist: PyQt5
Requires-Dist: numpy
Requires-Dist: pyqtgraph
Requires-Dist: python-dateutil
Requires-Dist: pytz
Requires-Dist: requests
Requires-Dist: tzlocal
